{
  "categoryPath": "/danh-muc/tay-te-bao-chet-da-mat-i.109",
  "categoryName": "Tẩy Tế Bào Chết Da Mặt",
  "page": 1,
  "url": "https://cocolux.com/danh-muc/tay-te-bao-chet-da-mat-i.109?page=1",
  "items": [
    {
      "categoryPath": "/danh-muc/tay-te-bao-chet-da-mat-i.109",
      "categoryName": "Tẩy Tế Bào Chết Da Mặt",
      "page": 1,
      "productName": "Tẩy Tế Bào Chết Paula' Choice Skin Perfecting 8% AHA Gel Exfoliant 15ml",
      "brandName": "Paula's Choice",
      "productUrl": "https://cocolux.com/tay-te-bao-chet-paula-choice-skin-perfecting-8-aha-gel-exfoliant-15ml-i.0655439019071",
      "imageUrl": "https://cocolux.com/storage/upload_image/images/tay-te-bao-chet-paula-choice-skin-perfecting-8-aha-gel-exfoliant-15ml.jpg",
      "price": 299000,
      "originalPrice": 399000,
      "discountPct": 25,
      "discountText": "25%",
      "ratingText": null,
      "salesText": "Đã bán 22",
      "crawledAt": "2026-04-14T19:36:49.487Z"
    },
    {
      "categoryPath": "/danh-muc/tay-te-bao-chet-da-mat-i.109",
      "categoryName": "Tẩy Tế Bào Chết Da Mặt",
      "page": 1,
      "productName": "Tẩy Tế Bào Chết Rosette Gommage Peeling Gel 120gr (Xanh)",
      "brandName": "ROSETTE",
      "productUrl": "https://cocolux.com/tay-te-bao-chet-rosette-gommage-peeling-gel-120gr-xanh-i.4901696542248",
      "imageUrl": "https://cocolux.com/storage/upload_image/files/gel-tay-te-bao-chet-rosette-gommage-gentle-120g-mau-xanh-mau-moi-3.jpg",
      "price": 115000,
      "originalPrice": null,
      "discountPct": null,
      "discountText": null,
      "ratingText": null,
      "salesText": "Đã bán 11.6k",
      "crawledAt": "2026-04-14T19:36:49.487Z"
    },
    {
      "categoryPath": "/danh-muc/tay-te-bao-chet-da-mat-i.109",
      "categoryName": "Tẩy Tế Bào Chết Da Mặt",
      "page": 1,
      "productName": "Tẩy Tế Bào Chết Rosette Gommage Bright Peel Dưỡng Sáng Da 120g (Vàng)",
      "brandName": "ROSETTE",
      "productUrl": "https://cocolux.com/tay-da-chet-rosette-gommage-bright-peel-duong-sang-da-120g-i.4901696542255",
      "imageUrl": "https://cocolux.com/storage/upload_image/images/tay-da-chet-rosette-gommage-bright-peel-duong-sang-da-120g.jpg",
      "price": 115000,
      "originalPrice": null,
      "discountPct": null,
      "discountText": null,
      "ratingText": null,
      "salesText": "Đã bán 11.6k",
      "crawledAt": "2026-04-14T19:36:49.487Z"
    },
    {
      "categoryPath": "/danh-muc/tay-te-bao-chet-da-mat-i.109",
      "categoryName": "Tẩy Tế Bào Chết Da Mặt",
      "page": 1,
      "productName": "Kem Tẩy Da Chết Paula's Choice Resist Daily Smoothing Treatment 5% AHA Giảm Khô Và Làm Mềm Da 10ml",
      "brandName": "Paula's Choice",
      "productUrl": "https://cocolux.com/kem-tay-da-chet-paulas-choice-resist-daily-smoothing-treatment-5-aha-giam-kho-va-lam-mem-da-10ml-i.0655439076678",
      "imageUrl": "https://cocolux.com/storage/upload_image/files/kem-tay-da-chet-paula-s-choice-resist-daily-smoothing-treatment-5-aha-10ml.jpg",
      "price": 374000,
      "originalPrice": 499000,
      "discountPct": 25,
      "discountText": "25%",
      "ratingText": null,
      "salesText": "Đã bán 0",
      "crawledAt": "2026-04-14T19:36:49.487Z"
    },
    {
      "categoryPath": "/danh-muc/tay-te-bao-chet-da-mat-i.109",
      "categoryName": "Tẩy Tế Bào Chết Da Mặt",
      "page": 1,
      "productName": "Dung Dịch Tẩy Da Chết Paula's Choice 6% Mandelic Acid + 2% Lactic Acid Dưỡng Ẩm Sáng Da & Làm Mờ Nếp Nhăn 88ml",
      "brandName": "Paula's Choice",
      "productUrl": "https://cocolux.com/dung-dich-tay-da-chet-paulas-choice-6-mandelic-acid-2-lactic-acid-duong-am-sang-da-lam-mo-nep-nhan-88ml-i.0655439014700",
      "imageUrl": "https://cocolux.com/storage/upload_image/files/dung-dich-tay-da-chet-paula-s-choice-6-mandelic-acid-2-lactic-acid.jpg",
      "price": 1150000,
      "originalPrice": null,
      "discountPct": null,
      "discountText": null,
      "ratingText": null,
      "salesText": "Đã bán 0",
      "crawledAt": "2026-04-14T19:36:49.487Z"
    },
    {
      "categoryPath": "/danh-muc/tay-te-bao-chet-da-mat-i.109",
      "categoryName": "Tẩy Tế Bào Chết Da Mặt",
      "page": 1,
      "productName": "Tẩy Tế Bào Chết Cure White Clear Gel 100g",
      "brandName": "CURE",
      "productUrl": "https://cocolux.com/tay-te-bao-chet-cure-white-clear-gel-100g-i.4589563520164",
      "imageUrl": "https://cocolux.com/storage/upload_image/images/tay-te-bao-chet-cure-white-clear-gel-100g.jpg",
      "price": 285000,
      "originalPrice": null,
      "discountPct": null,
      "discountText": null,
      "ratingText": null,
      "salesText": "Đã bán 0",
      "crawledAt": "2026-04-14T19:36:49.487Z"
    },
    {
      "categoryPath": "/danh-muc/tay-te-bao-chet-da-mat-i.109",
      "categoryName": "Tẩy Tế Bào Chết Da Mặt",
      "page": 1,
      "productName": "Tẩy Tế Bào Chết Cure Natural Aqua Gel 100g",
      "brandName": "CURE",
      "productUrl": "https://cocolux.com/tay-te-bao-chet-cure-natural-aqua-gel-100g-i.4589563520126",
      "imageUrl": "https://cocolux.com/upload/product/tay-te-bao-chet-da-mat/tay-te-bao-chet-cure-natural-aqua-gel-100g-4.webp",
      "price": 285000,
      "originalPrice": null,
      "discountPct": null,
      "discountText": null,
      "ratingText": null,
      "salesText": "Đã bán 0",
      "crawledAt": "2026-04-14T19:36:49.487Z"
    },
    {
      "categoryPath": "/danh-muc/tay-te-bao-chet-da-mat-i.109",
      "categoryName": "Tẩy Tế Bào Chết Da Mặt",
      "page": 1,
      "productName": "Tẩy Tế Bào Chết Da Mặt Cocoon Dak Lak Coffee Face Polish Cà Phê Đắk Lắk 150ml (Mã Mới)",
      "brandName": "COCOON",
      "productUrl": "https://cocolux.com/tay-te-bao-chet-da-mat-cocoon-dak-lak-coffee-face-polish-150ml-i.8936217700018",
      "imageUrl": "https://cocolux.com/storage/upload_image/images/cdn_images/2023/05/images/products/1684124989566-tay-te-bao-da-mat-cocoon-ca-phe-daklak.jpeg",
      "price": 165000,
      "originalPrice": null,
      "discountPct": null,
      "discountText": null,
      "ratingText": null,
      "salesText": "Đã bán 697",
      "crawledAt": "2026-04-14T19:36:49.487Z"
    },
    {
      "categoryPath": "/danh-muc/tay-te-bao-chet-da-mat-i.109",
      "categoryName": "Tẩy Tế Bào Chết Da Mặt",
      "page": 1,
      "productName": "Tẩy Tế Bào Chết Huxley Scrub Mask: Sweet Therapy mini 30g",
      "brandName": "HUXLEY",
      "productUrl": "https://cocolux.com/tay-da-chet-huxley-scrub-mask-therapy-mini-i.8809422533187",
      "imageUrl": "https://cocolux.com/storage/upload_image/images/Bao_bi_moi/Thay-sp/8809422533187.jpg",
      "price": 99000,
      "originalPrice": 120000,
      "discountPct": 18,
      "discountText": "18%",
      "ratingText": null,
      "salesText": "Đã bán 1.9k",
      "crawledAt": "2026-04-14T19:36:49.487Z"
    },
    {
      "categoryPath": "/danh-muc/tay-te-bao-chet-da-mat-i.109",
      "categoryName": "Tẩy Tế Bào Chết Da Mặt",
      "page": 1,
      "productName": "Gel Tẩy Tế Bào Chết Caryophy Ngăn Ngừa Mụn 250ml Smart Peeling Gel",
      "brandName": "CARYOPHY",
      "productUrl": "https://cocolux.com/gel-tay-te-bao-chet-caryophy-ngan-ngua-mun-250ml-smart-peeling-gel-i.8809501251186",
      "imageUrl": "https://cocolux.com/storage/upload_image/images/cdn_images/2022/10/images/products/1666075338234-gel-tay-te-bao-chet-caryophy-ngan-ngua-mun-250ml-smart-peeling-gel-01.jpeg",
      "price": 338000,
      "originalPrice": 450000,
      "discountPct": 25,
      "discountText": "25%",
      "ratingText": null,
      "salesText": "Đã bán 0",
      "crawledAt": "2026-04-14T19:36:49.487Z"
    },
    {
      "categoryPath": "/danh-muc/tay-te-bao-chet-da-mat-i.109",
      "categoryName": "Tẩy Tế Bào Chết Da Mặt",
      "page": 1,
      "productName": "Tẩy Tế Bào Chết Paula's Choice 2% BHA 118ml",
      "brandName": "Paula's Choice",
      "productUrl": "https://cocolux.com/tay-te-bao-chet-paulas-choice-2-bha-118ml-i.0655439020107",
      "imageUrl": "https://cocolux.com/storage/upload_image/images/cdn_images/2021/08/images/products/1630388500315-dung-dich-tay-da-chet-paulas-choice-bha-118ml.jpeg",
      "price": 734000,
      "originalPrice": 979000,
      "discountPct": 25,
      "discountText": "25%",
      "ratingText": null,
      "salesText": "Đã bán 419",
      "crawledAt": "2026-04-14T19:36:49.487Z"
    },
    {
      "categoryPath": "/danh-muc/tay-te-bao-chet-da-mat-i.109",
      "categoryName": "Tẩy Tế Bào Chết Da Mặt",
      "page": 1,
      "productName": "Tẩy Tế Bào Chết Mặt Bio-Essence Dưỡng Da Tươi Trẻ 60g",
      "brandName": "BIO-ESSENCE",
      "productUrl": "https://cocolux.com/tay-te-bao-chet-bio-essence-renew-60g-i.8888176027371",
      "imageUrl": "https://cocolux.com/storage/upload_image/images/Bao_bi_moi/Thay-sp/8888176027371.jpg",
      "price": 326000,
      "originalPrice": null,
      "discountPct": null,
      "discountText": null,
      "ratingText": null,
      "salesText": "Đã bán 1.6k",
      "crawledAt": "2026-04-14T19:36:49.487Z"
    },
    {
      "categoryPath": "/danh-muc/tay-te-bao-chet-da-mat-i.109",
      "categoryName": "Tẩy Tế Bào Chết Da Mặt",
      "page": 1,
      "productName": "Tẩy Tế Bào Chết Da Mặt EUCERIN Pro ACNE Solution Scrub Ngăn Ngừa Mụn 100ml",
      "brandName": "EUCERIN",
      "productUrl": "https://cocolux.com/tay-te-bao-chet-eucerin-ngan-ngua-mun-100ml-i.8850029022659",
      "imageUrl": "https://cocolux.com/storage/upload_image/images/Bao_bi_moi/Thay-sp/8850029022659.jpg",
      "price": 349000,
      "originalPrice": 389000,
      "discountPct": 10,
      "discountText": "10%",
      "ratingText": null,
      "salesText": "Đã bán 1.3k",
      "crawledAt": "2026-04-14T19:36:49.487Z"
    },
    {
      "categoryPath": "/danh-muc/tay-te-bao-chet-da-mat-i.109",
      "categoryName": "Tẩy Tế Bào Chết Da Mặt",
      "page": 1,
      "productName": "Tẩy Tế Bào Chết Da Mặt Naruko Tea Tree Cho Da Dầu Mụn 120ml",
      "brandName": "NARUKO",
      "productUrl": "https://cocolux.com/gel-tay-te-bao-chet-cho-da-dau-mun-naruko-tea-tree-120ml-i.4711542264435",
      "imageUrl": "https://cocolux.com/storage/upload_image/images/Bao_bi_moi/Thay-sp/4711542264435.jpg",
      "price": 259000,
      "originalPrice": 309000,
      "discountPct": 16,
      "discountText": "16%",
      "ratingText": null,
      "salesText": "Đã bán 1.5k",
      "crawledAt": "2026-04-14T19:36:49.487Z"
    },
    {
      "categoryPath": "/danh-muc/tay-te-bao-chet-da-mat-i.109",
      "categoryName": "Tẩy Tế Bào Chết Da Mặt",
      "page": 1,
      "productName": "Tẩy Da Chết Huxley Fullsize 120ml",
      "brandName": "HUXLEY",
      "productUrl": "https://cocolux.com/tay-da-chet-huxley-fullsize-i.8809422534047",
      "imageUrl": "https://cocolux.com/storage/upload_image/images/cdn_images/2020/12/products/1608868118966-huxley-scrub-mask-sweet-therapy.jpeg",
      "price": 285000,
      "originalPrice": null,
      "discountPct": null,
      "discountText": null,
      "ratingText": null,
      "salesText": "Đã bán 610",
      "crawledAt": "2026-04-14T19:36:49.487Z"
    },
    {
      "categoryPath": "/danh-muc/tay-te-bao-chet-da-mat-i.109",
      "categoryName": "Tẩy Tế Bào Chết Da Mặt",
      "page": 1,
      "productName": "Tẩy Tế Bào Chết Cure Natural Aqua Gel 250g",
      "brandName": "CURE",
      "productUrl": "https://cocolux.com/tay-da-chet-cure-natural-aqua-gel-250g-i.4589563520102",
      "imageUrl": "https://cocolux.com/storage/upload_image/images/cdn_images/2020/12/products/1608534361861-tdc-gel-cure-(chai)-4.jpeg",
      "price": 500000,
      "originalPrice": null,
      "discountPct": null,
      "discountText": null,
      "ratingText": null,
      "salesText": "Đã bán 824",
      "crawledAt": "2026-04-14T19:36:49.487Z"
    },
    {
      "categoryPath": "/danh-muc/tay-te-bao-chet-da-mat-i.109",
      "categoryName": "Tẩy Tế Bào Chết Da Mặt",
      "page": 1,
      "productName": "Tẩy Da Chết Bioderma Sebium Gel Gommant 100ml",
      "brandName": "BIODERMA",
      "productUrl": "https://cocolux.com/tay-da-chet-bioderma-sebium-gel-gommant-100ml-i.3401574131423",
      "imageUrl": "https://cocolux.com/storage/upload_image/images/cdn_images/2021/08/images/products/1629777033710-tay-da-chet-bioderma-sebium-gel-gommant-100ml.png",
      "price": 428000,
      "originalPrice": 450000,
      "discountPct": 5,
      "discountText": "5%",
      "ratingText": null,
      "salesText": "Đã bán 367",
      "crawledAt": "2026-04-14T19:36:49.487Z"
    },
    {
      "categoryPath": "/danh-muc/tay-te-bao-chet-da-mat-i.109",
      "categoryName": "Tẩy Tế Bào Chết Da Mặt",
      "page": 1,
      "productName": "Tẩy Da Chết DR.PEPTI Herb Natural Peeling Gel 130ml",
      "brandName": "DR.PEPTI",
      "productUrl": "https://cocolux.com/tay-da-chet-dr-pepti-herb-natural-peeling-gel-130ml-i.8809451338005",
      "imageUrl": "https://cocolux.com/storage/upload_image/images/san-pham/tay-da-chet-dr-pepti-herb-natural-peeling-gel-130ml.jpg",
      "price": 167000,
      "originalPrice": 185000,
      "discountPct": 10,
      "discountText": "10%",
      "ratingText": null,
      "salesText": "Đã bán 50",
      "crawledAt": "2026-04-14T19:36:49.487Z"
    },
    {
      "categoryPath": "/danh-muc/tay-te-bao-chet-da-mat-i.109",
      "categoryName": "Tẩy Tế Bào Chết Da Mặt",
      "page": 1,
      "productName": "Dung Dịch Tẩy Da Chết Paula’s Choice Skin Perfecting 2% BHA Liquid 30ml",
      "brandName": "Paula's Choice",
      "productUrl": "https://cocolux.com/dung-dich-loai-bo-te-bao-chet-2-bha-paulas-choice-i.0655439020169",
      "imageUrl": "https://cocolux.com/storage/upload_image/images/cdn_images/2021/05/products/1621478830694-dung-dich-loai-bo-te-bao-chet-bha-paulas-choice-30ml.png",
      "price": 399000,
      "originalPrice": null,
      "discountPct": null,
      "discountText": null,
      "ratingText": null,
      "salesText": "Đã bán 419",
      "crawledAt": "2026-04-14T19:36:49.487Z"
    },
    {
      "categoryPath": "/danh-muc/tay-te-bao-chet-da-mat-i.109",
      "categoryName": "Tẩy Tế Bào Chết Da Mặt",
      "page": 1,
      "productName": "Tẩy Tế Bào Chết Da Mặt Paula's Choice 8% AHA Dạng Gel 100ml",
      "brandName": "Paula's Choice",
      "productUrl": "https://cocolux.com/tay-te-bao-chet-da-mat-paulas-choice-8-aha-dang-gel-100ml-i.0655439019002",
      "imageUrl": "https://cocolux.com/storage/upload_image/images/cdn_images/2021/05/products/1621479997545-gel-loai-bo-te-bao-chet-paulas-choice-aha-100ml.jpeg",
      "price": 712000,
      "originalPrice": 949000,
      "discountPct": 25,
      "discountText": "25%",
      "ratingText": null,
      "salesText": "Đã bán 22",
      "crawledAt": "2026-04-14T19:36:49.487Z"
    },
    {
      "categoryPath": "/danh-muc/tay-te-bao-chet-da-mat-i.109",
      "categoryName": "Tẩy Tế Bào Chết Da Mặt",
      "page": 1,
      "productName": "Tẩy Tế Bào Chết Dr.Pepti Centella Turnover Soft Peeling Gel AHA PHA LHA 100ml",
      "brandName": "DR.PEPTI",
      "productUrl": "https://cocolux.com/tay-te-bao-chet-drpepti-centella-turnover-soft-peeling-gel-aha-pha-lha-100ml-i.8809610272836",
      "imageUrl": "https://cocolux.com/upload/product/8809610272836.webp",
      "price": 275000,
      "originalPrice": 305000,
      "discountPct": 9.84,
      "discountText": null,
      "ratingText": null,
      "salesText": null,
      "crawledAt": "2026-04-14T19:36:49.487Z"
    },
    {
      "categoryPath": "/danh-muc/tay-te-bao-chet-da-mat-i.109",
      "categoryName": "Tẩy Tế Bào Chết Da Mặt",
      "page": 1,
      "productName": "Tẩy Tế Bào Chết Arrahan Premium Moisturizing Peeling Gel Pearl Tone Up 180ml Ngọc Trai",
      "brandName": "ARRAHAN",
      "productUrl": "https://cocolux.com/tay-te-bao-chet-arrahan-premium-moisturizing-peeling-gel-pearl-tone-up-180ml-ngoc-trai-i.8809617812967",
      "imageUrl": "https://cocolux.com/upload/product/8809617812967.webp",
      "price": 99000,
      "originalPrice": 120000,
      "discountPct": 17.5,
      "discountText": null,
      "ratingText": null,
      "salesText": null,
      "crawledAt": "2026-04-14T19:36:49.487Z"
    },
    {
      "categoryPath": "/danh-muc/tay-te-bao-chet-da-mat-i.109",
      "categoryName": "Tẩy Tế Bào Chết Da Mặt",
      "page": 1,
      "productName": "Tẩy Tế Bào Chết Arrahan Premium Moisturizing Peeling Gel Green Tea 180ml Trà Xanh",
      "brandName": "ARRAHAN",
      "productUrl": "https://cocolux.com/tay-te-bao-chet-arrahan-premium-moisturizing-peeling-gel-green-tea-180ml-tra-xanh-i.8809617812950",
      "imageUrl": "https://cocolux.com/upload/product/8809617812950.webp",
      "price": 99000,
      "originalPrice": 120000,
      "discountPct": 17.5,
      "discountText": null,
      "ratingText": null,
      "salesText": null,
      "crawledAt": "2026-04-14T19:36:49.487Z"
    },
    {
      "categoryPath": "/danh-muc/tay-te-bao-chet-da-mat-i.109",
      "categoryName": "Tẩy Tế Bào Chết Da Mặt",
      "page": 1,
      "productName": "Dưỡng Chất Loreal Glycolic Làm Sạch Tế Bào Chết 25ml",
      "brandName": "L'ORÉAL",
      "productUrl": "https://cocolux.com/duong-chat-loreal-glycolic-lam-sach-te-bao-chet-25ml-i.8994993027316",
      "imageUrl": "https://cocolux.com/upload/product/8994993027316.webp",
      "price": 484000,
      "originalPrice": 509000,
      "discountPct": 4.91,
      "discountText": null,
      "ratingText": null,
      "salesText": null,
      "crawledAt": "2026-04-14T19:36:49.487Z"
    },
    {
      "categoryPath": "/danh-muc/tay-te-bao-chet-da-mat-i.109",
      "categoryName": "Tẩy Tế Bào Chết Da Mặt",
      "page": 1,
      "productName": "Tẩy Da Chết Cure White Clear Gel 200g",
      "brandName": "CURE",
      "productUrl": "https://cocolux.com/tay-da-chet-cure-white-clear-gel-200g-i.4589563520157",
      "imageUrl": "https://cocolux.com/upload/product/4589563520157.webp",
      "price": 558000,
      "originalPrice": null,
      "discountPct": null,
      "discountText": null,
      "ratingText": null,
      "salesText": null,
      "crawledAt": "2026-04-14T19:36:49.487Z"
    },
    {
      "categoryPath": "/danh-muc/tay-te-bao-chet-da-mat-i.109",
      "categoryName": "Tẩy Tế Bào Chết Da Mặt",
      "page": 1,
      "productName": "Tẩy Da Chết Dr.G Brightening Peeling Gel 120g",
      "brandName": "DR.G",
      "productUrl": "https://cocolux.com/tay-da-chet-drg-brightening-peeling-gel-120g-i.8809838651635",
      "imageUrl": "https://cocolux.com/upload/product/8809838651635.webp",
      "price": 351900,
      "originalPrice": 391000,
      "discountPct": 10,
      "discountText": null,
      "ratingText": null,
      "salesText": null,
      "crawledAt": "2026-04-14T19:36:49.487Z"
    },
    {
      "categoryPath": "/danh-muc/tay-te-bao-chet-da-mat-i.109",
      "categoryName": "Tẩy Tế Bào Chết Da Mặt",
      "page": 1,
      "productName": "Dung Dịch Tẩy Da Chết Obagi Clenziderm M.D Pore Therapy Exfoliating 2% BHA 148ml",
      "brandName": "OBAGI",
      "productUrl": "https://cocolux.com/dung-dich-tay-da-chet-obagi-clenziderm-md-pore-therapy-exfoliating-2-bha-148ml-i.362032612805",
      "imageUrl": "https://cocolux.com/upload/product/tay-te-bao-chet-da-mat/dung-dich-tay-da-chet-obagi-clenziderm-md-pore-therapy-exfoliating-2-bha-148ml.webp",
      "price": 1125000,
      "originalPrice": 1250000,
      "discountPct": 10,
      "discountText": "10%",
      "ratingText": null,
      "salesText": "Đã bán 0",
      "crawledAt": "2026-04-14T19:36:49.487Z"
    },
    {
      "categoryPath": "/danh-muc/tay-te-bao-chet-da-mat-i.109",
      "categoryName": "Tẩy Tế Bào Chết Da Mặt",
      "page": 1,
      "productName": "Gel Tẩy Tế Bào Chết Round Lab 1025 Dokdo Peeling Gel 120ml",
      "brandName": "ROUND LAB",
      "productUrl": "https://cocolux.com/gel-tay-te-bao-chet-round-lab-1025-dokdo-peeling-gel-120ml-i.8809783321966",
      "imageUrl": "https://cocolux.com/storage/upload_image/files/gel-tay-te-bao-chet-round-lab-1025-dokdo-peeling-gel-120ml.jpg",
      "price": 365000,
      "originalPrice": null,
      "discountPct": null,
      "discountText": null,
      "ratingText": null,
      "salesText": "Đã bán 0",
      "crawledAt": "2026-04-14T19:36:49.487Z"
    },
    {
      "categoryPath": "/danh-muc/tay-te-bao-chet-da-mat-i.109",
      "categoryName": "Tẩy Tế Bào Chết Da Mặt",
      "page": 1,
      "productName": "Serum Tẩy Da Chết Dr.Melaxin Exosome Peeling 50ml",
      "brandName": "Đang cập nhật",
      "productUrl": "https://cocolux.com/serum-tay-da-chet-drmelaxin-exosome-peeling-50ml-i.8809886481338",
      "imageUrl": "https://cocolux.com/storage/upload_image/images/san-pham/serum-tay-da-chet-drmelaxin-exosome-peeling-50ml.jpg",
      "price": 490000,
      "originalPrice": null,
      "discountPct": null,
      "discountText": null,
      "ratingText": null,
      "salesText": "Đã bán 0",
      "crawledAt": "2026-04-14T19:36:49.487Z"
    },
    {
      "categoryPath": "/danh-muc/tay-te-bao-chet-da-mat-i.109",
      "categoryName": "Tẩy Tế Bào Chết Da Mặt",
      "page": 1,
      "productName": "Dung Dịch Tẩy Tế Bào Da Chết Emmié by Happyskin Exfoliating Solutions Toner 7% AHA + PHA 140ml",
      "brandName": "Đang cập nhật",
      "productUrl": "https://cocolux.com/dung-dich-tay-te-bao-da-chet-emmie-by-happyskin-exfoliating-solutions-toner-7-aha-pha-140ml-i.8938552514701",
      "imageUrl": "https://cocolux.com/storage/upload_image/images/san-pham/dung-dich-tay-te-bao-da-chet-emmie-by-happyskin-exfoliating-solutions-toner-7-aha-pha-140ml.jpg",
      "price": 329000,
      "originalPrice": null,
      "discountPct": null,
      "discountText": null,
      "ratingText": null,
      "salesText": "Đã bán 0",
      "crawledAt": "2026-04-14T19:36:49.487Z"
    },
    {
      "categoryPath": "/danh-muc/tay-te-bao-chet-da-mat-i.109",
      "categoryName": "Tẩy Tế Bào Chết Da Mặt",
      "page": 1,
      "productName": "Dung Dịch Tẩy Tế Bào Chết All Target Skin Renewing Solution Pionin + 12% AHA/BHA/PHA 120ml",
      "brandName": "Đang cập nhật",
      "productUrl": "https://cocolux.com/dung-dich-tay-te-bao-chet-all-target-skin-renewing-solution-pionin-12-ahabhapha-120ml-i.8938552514008",
      "imageUrl": "https://cocolux.com/storage/upload_image/images/dung-dich-tay-te-bao-chet-all-target-skin-renewing-solution-pionin-12-ahabhapha-120ml.jpg",
      "price": 360000,
      "originalPrice": null,
      "discountPct": null,
      "discountText": null,
      "ratingText": null,
      "salesText": "Đã bán 0",
      "crawledAt": "2026-04-14T19:36:49.487Z"
    },
    {
      "categoryPath": "/danh-muc/tay-te-bao-chet-da-mat-i.109",
      "categoryName": "Tẩy Tế Bào Chết Da Mặt",
      "page": 1,
      "productName": "Tẩy Tế Bào Da Chết Mặt Bergamo Quýt Xanh Trắng Da 150ml",
      "brandName": "Bergamo",
      "productUrl": "https://cocolux.com/tay-da-chet-bergamo-quyt-xanh-trang-da-150ml-i.8809414193146",
      "imageUrl": "https://cocolux.com/storage/upload_image/images/tay-da-chet-bergamo-quyt-xanh-trang-da-150ml.jpg",
      "price": 205000,
      "originalPrice": null,
      "discountPct": null,
      "discountText": null,
      "ratingText": null,
      "salesText": "Đã bán 0",
      "crawledAt": "2026-04-14T19:36:49.487Z"
    },
    {
      "categoryPath": "/danh-muc/tay-te-bao-chet-da-mat-i.109",
      "categoryName": "Tẩy Tế Bào Chết Da Mặt",
      "page": 1,
      "productName": "Tẩy Tế Bào Chết Paula's Choice 1% BHA Cho Da Nhạy Cảm 100ml",
      "brandName": "Paula's Choice",
      "productUrl": "https://cocolux.com/tay-te-bao-chet-paula-choice-1-bha-cho-da-nhay-cam-100ml-i.0655439091008",
      "imageUrl": "https://cocolux.com/storage/upload_image/images/cdn_images/2021/08/images/products/1630389120306-tay-te-bao-chet-paulas-choice-da-nhay-cam-100ml.jpeg",
      "price": 949000,
      "originalPrice": null,
      "discountPct": null,
      "discountText": null,
      "ratingText": null,
      "salesText": "Đã bán 72",
      "crawledAt": "2026-04-14T19:36:49.487Z"
    },
    {
      "categoryPath": "/danh-muc/tay-te-bao-chet-da-mat-i.109",
      "categoryName": "Tẩy Tế Bào Chết Da Mặt",
      "page": 1,
      "productName": "Tẩy Tế Bào Chết Mặt The Face Shop Smart Peeling White Jewel Perle Ngọc Trai 120ml",
      "brandName": "THE FACE SHOP",
      "productUrl": "https://cocolux.com/tay-da-chet-ngoc-trai-the-face-shop-i.8806182572500",
      "imageUrl": "https://cocolux.com/storage/upload_image/images/cdn_images/2022/02/images/products/1644978167427-tay-da-chet-ngoc-trai-the-face-shop.jpeg",
      "price": 185000,
      "originalPrice": null,
      "discountPct": null,
      "discountText": null,
      "ratingText": null,
      "salesText": "Đã bán 2.2k",
      "crawledAt": "2026-04-14T19:36:49.487Z"
    },
    {
      "categoryPath": "/danh-muc/tay-te-bao-chet-da-mat-i.109",
      "categoryName": "Tẩy Tế Bào Chết Da Mặt",
      "page": 1,
      "productName": "Tẩy Da Chết Rosette Gommage Moist Peeling Gel Dành Cho Da Khô",
      "brandName": "ROSETTE",
      "productUrl": "https://cocolux.com/tay-da-chet-rosette-da-kho-i.4901696536407",
      "imageUrl": "https://cocolux.com/storage/upload_image/images/cdn_images/2021/08/images/products/1629039164689-tay-da-chet-rosette.jpeg",
      "price": 115000,
      "originalPrice": null,
      "discountPct": null,
      "discountText": null,
      "ratingText": null,
      "salesText": "Đã bán 11.6k",
      "crawledAt": "2026-04-14T19:36:49.487Z"
    }
  ],
  "crawledAt": "2026-04-14T19:36:49.487Z"
}