{
  "url": "https://hasaki.vn/san-pham/ao-hai-day-nu-synctives-mem-mai-sieu-thoang-khi-do-samba-s-223141.html",
  "name": "Áo Hai Dây Nữ Synctives Slim Fit, USA Cotton, Đỏ Samba, Size S",
  "brandName": "Synctives",
  "barcode": "422281974",
  "statusText": "Còn hàng",
  "inStock": true,
  "remainingQuantityText": null,
  "branchesInStockText": null,
  "price": 59000,
  "originalPrice": 59000,
  "flashSalePrice": 59000,
  "discountPct": 0,
  "description": null,
  "benefits": null,
  "usage": null,
  "ingredients": null,
  "breadcrumb": [],
  "galleryImages": [
    "https://media.hcdn.vn/catalog/product/p/r/facebook-dynamic-ao-hai-day-nu-synctives-mem-mai-sieu-thoang-khi-do-samba-s_qkfx5May5T1fqaoR.png"
  ],
  "crawledAt": "2026-04-14T20:36:27.047Z"
}