{
  "url": "https://hasaki.vn/san-pham/combo-8-bang-ve-sinh-kotex-mini-meow-sieu-mem-canh-24cm-8-mieng-194525.html",
  "name": "Combo 8 Băng Vệ Sinh Kotex Mini Meow Siêu Mềm Cánh 24cm 8 Miếng",
  "brandName": "Kotex",
  "barcode": "422268004",
  "statusText": "Còn hàng",
  "inStock": true,
  "remainingQuantityText": null,
  "branchesInStockText": null,
  "price": 172000,
  "originalPrice": 172000,
  "flashSalePrice": 172000,
  "discountPct": 0,
  "description": null,
  "benefits": null,
  "usage": null,
  "ingredients": null,
  "breadcrumb": [],
  "galleryImages": [
    "https://media.hcdn.vn/catalog/product/p/r/special-deal-combo-8-bang-ve-sinh-kotex-mini-meow-sieu-mem-canh-24cm-8-mieng_9JhSkJhr94GLPz5W.png"
  ],
  "crawledAt": "2026-04-14T20:00:05.827Z"
}