{
  "url": "https://hasaki.vn/san-pham/bang-ve-sinh-kotex-hoa-anh-dao-sieu-mong-canh-23cm-20-mieng-102229.html",
  "name": "Băng Vệ Sinh Kotex Hoa Anh Đào Siêu Mỏng Cánh 23cm 20 Miếng",
  "brandName": "Kotex",
  "barcode": "422208205",
  "statusText": "Còn hàng",
  "inStock": true,
  "remainingQuantityText": null,
  "branchesInStockText": null,
  "price": 46000,
  "originalPrice": 46000,
  "flashSalePrice": 46000,
  "discountPct": 0,
  "description": null,
  "benefits": null,
  "usage": null,
  "ingredients": null,
  "breadcrumb": [],
  "galleryImages": [
    "https://media.hcdn.vn/catalog/product/f/a/facebook-dynamic-bang-ve-sinh-kotex-hoa-anh-dao-sieu-mong-canh-23cm-20-mieng-1773022425.jpg"
  ],
  "crawledAt": "2026-04-14T19:57:01.329Z"
}