{
  "url": "https://hasaki.vn/san-pham/ao-hai-day-nu-synctives-mem-mai-sieu-thoang-khi-xanh-den-xl-223073.html",
  "name": "Áo Hai Dây Nữ Synctives Slim Fit, USA Cotton, Xanh Đen, Size XL",
  "brandName": "Synctives",
  "barcode": "422281957",
  "statusText": "Còn hàng",
  "inStock": true,
  "remainingQuantityText": null,
  "branchesInStockText": null,
  "price": 59000,
  "originalPrice": 59000,
  "flashSalePrice": 59000,
  "discountPct": 0,
  "description": null,
  "benefits": null,
  "usage": null,
  "ingredients": null,
  "breadcrumb": [],
  "galleryImages": [
    "https://media.hcdn.vn/catalog/product/p/r/facebook-dynamic-ao-hai-day-nu-synctives-mem-mai-sieu-thoang-khi-xanh-den-xl_z2Vujo2XsYZ5DW29.png"
  ],
  "crawledAt": "2026-04-14T20:36:04.519Z"
}