{
  "url": "https://cocolux.com/mat-na-queen-helene-mint-julep-masque-i.079896585793",
  "name": "Mặt Nạ Đất Sét Queen Helene Mint Julep Masque",
  "brandName": "QUEEN HELENE",
  "barcode": "079896585793",
  "statusText": "Hết hàng",
  "inStock": false,
  "remainingQuantityText": null,
  "branchesInStockText": null,
  "price": 165000,
  "originalPrice": 165000,
  "flashSalePrice": 165000,
  "discountPct": 0,
  "description": "Queen Helene là thương hiệu mỹ phẩm được thành lập năm 1930 tại Pháp. Đến nay hãng đã có hơn 80 năm kinh nghiệm trong lĩnh vực chăm sóc sắc đẹp và được phân phối tại nhiều quốc gia trên khắp thế giới. Có thể dễ nhận thấy điểm chung trong các sản phẩm của hãng là sử dụng các thành phần thiên nhiên có lợi, lành tính, an toàn với mọi loại da, mang đến hiệu quả cao và giúp cải thiện mọi vấn đề cho da của bạn. Mặt Nạ Queen Helene Mint Julep Masque là một trong những sản phẩm nổi bật của hãng được nhiều khách hàng vô cùng yêu thích. Sản phẩm phù hợp với mọi làn da, bao gồm cả làn da hay kích ứng, dễ nhạy cảm. Nhưng nếu xét về thành phần thì mặt nạ được đánh giá là phù hợp hơn với làn da dầu, mụn hoặc da hỗn hợp thiên dầu. Với thành phần chính là chiết xuất bạc hà và kaolin, chính là công thức tối ưu giúp làm sạch da mặt, loại bỏ bụi bẩn, tạp chất cũng như kháng khuẩn, ngừa mụn mang đến cho bạn làn da sạch khỏe, tươi tắn rạng ngời. Với chất kem màu xanh dịu mát và hương thơm dễ chịu, mặt nạ Queen Helene Mint Julep Masque hứa hẹn mang đến cho các nàng cảm giác thư giãn mỗi lần sử dụng.",
  "benefits": null,
  "usage": null,
  "ingredients": null,
  "breadcrumb": [
    "Trang chủ",
    "Mặt Nạ Rửa"
  ],
  "galleryImages": [
    "https://cocolux.com/storage/upload_image/images/cdn_images/2020/12/products/1608626891956-mat-na-queen-helene-mint-julep-masque-1.jpeg"
  ],
  "crawledAt": "2026-04-14T20:23:28.734Z"
}