{
  "url": "https://cocolux.com/sua-duong-da-la-roche-posay-duong-am-lam-diu-da-toleriane-40ml-mb064500-i.3337875588676",
  "name": "Sữa Dưỡng La Roche-Posay Làm Dịu Và Bảo Vệ Da 40ml",
  "brandName": "LA ROCHE-POSAY",
  "barcode": "3337875588676",
  "statusText": "Hết hàng",
  "inStock": false,
  "remainingQuantityText": null,
  "branchesInStockText": null,
  "price": 599000,
  "originalPrice": 599000,
  "flashSalePrice": 599000,
  "discountPct": 0,
  "description": "Sữa Dưỡng Da La Roche Posay dưỡng ẩm làm dịu da Toleriane 40ml là một sản phẩm mà các cô nàng có làn da nhạy cảm dễ bị kích ứng không nên bỏ qua. Sữa Dưỡng Da La Roche Posay dưỡng ẩm làm dịu da Toleriane 40ml nằm trong dòng sản phẩm Toleriane giúp dưỡng ẩm, làm dịu và bảo vệ làn da nhạy cảm, dễ bị kích ứng. Sản phẩm nổi bật với thành phần chứa nước khoáng La Roche Posay nhiều khoáng chất, nguyên tố vi lượng và selen, giúp làm sạch, làm mát và dịu da, giảm kích ứng, tăng cường lớp hàng rào bảo vệ tự nhiên của da, chống oxy hóa. Glycerin giúp dưỡng ẩm, cung cấp độ ẩm cho da bằng cách hấp thụ nước từ môi trường xung quanh. Niacinamide giúp dưỡng sáng da, tái tạo và phục hồi vùng da bị tổn thương, kích thích các tế bào da hoạt động và phát triển, tạo lớp hàng rào bảo vệ da. Toleriane Sensitive Fluide có kết cấu dạng sữa, mỏng nhẹ, thẩm thấu nhanh vào da, không gây nhờn rít, không làm bít tắc lỗ chân lông, không để lại vệt trắng trên da. Sản phẩm giúp hydrat hóa đến 48 giờ và bổ sung hàng rào độ ẩm cho da. Sữa Dưỡng Da La Roche Posay chứa các thành phần lành tính, an toàn cho da, phù hợp với da nhạy cảm, da dầu và da hỗn hợp.",
  "benefits": null,
  "usage": null,
  "ingredients": null,
  "breadcrumb": [
    "Trang chủ",
    "Lotion/Sữa Dưỡng"
  ],
  "galleryImages": [
    "https://cocolux.com/storage/upload_image/images/cdn_images/2021/03/products/1616475664490-Toleriane-Sensitive-Fluide-.jpeg"
  ],
  "crawledAt": "2026-04-14T20:19:39.350Z"
}