{
  "url": "https://cocolux.com/gel-tam-tao-bot-roger-gallet-fleur-dosmanthus-wellbeing-shower-200ml-i.3701436908089",
  "name": "Gel Tắm Tạo Bọt Roger & Gallet Fleur D'osmanthus Wellbeing Shower 200ml",
  "brandName": "ROGER &amp; GALLET",
  "barcode": "3701436908089",
  "statusText": "Hết hàng",
  "inStock": false,
  "remainingQuantityText": "Còn 5 sản phẩm",
  "branchesInStockText": null,
  "price": 300000,
  "originalPrice": 315000,
  "flashSalePrice": 300000,
  "discountPct": 4.76,
  "description": "Gel tắm tạo bọt Roger & Gallet là dòng sản phẩm cao cấp từ Pháp, kết hợp giữa hương thơm nước hoa tinh tế và công thức làm sạch dịu nhẹ từ thiên nhiên. Với 100% thành phần làm sạch từ gốc thực vật và chiết xuất nha đam, sản phẩm không chỉ làm sạch mà còn cung cấp độ ẩm, giữ làn da mềm mịn và lưu lại hương thơm nhẹ nhàng. Sản phẩm phù hợp với mọi loại da, kể cả da nhạy cảm, gel tắm này mang lại trải nghiệm thư giãn, sang trọng ngay tại nhà. Hiện Gel tắm tạo bọt Roger & Gallet đang được phân phối tại Cocolux với các phân loại: Rose (Hương Hoa Hồng): Hương thơm ngọt ngào, thanh lịch từ hoa hồng Đan Mạch, mang lại cảm giác thư thái và dễ chịu. Fleur De Figuier (Hương Quả Sung): Hương thơm tươi mới, ấm áp từ quả sung chín và bưởi chùm, giúp bạn tràn đầy sức sống. Fleur D’osmanthus (Hương Hoa Mộc Tê): Mùi hương thanh mát, nhẹ nhàng từ hoa mộc tê và trái đào chín, lý tưởng để xoa dịu tâm trạng. Gingembre Rouge (Hương Quả Mọng): Hương thơm lôi cuốn từ quả mọng và gừng đỏ, kích thích giác quan và tạo cảm giác sảng khoái. Cédrat (Hương Thanh Yên): Hương thơm sảng khoái, tươi mát từ thanh yên và cam chanh, mang đến nguồn năng lượng tích cực.",
  "benefits": null,
  "usage": null,
  "ingredients": null,
  "breadcrumb": [
    "Trang chủ",
    "Sữa Tắm"
  ],
  "galleryImages": [
    "https://cocolux.com/storage/upload_image/files/gel-tam-tao-bot-roger-gallet-fleur-d-osmanthus-wellbeing-shower-3.jpg"
  ],
  "crawledAt": "2026-04-14T19:43:07.616Z"
}