{
  "url": "https://cocolux.com/xa-phong-tao-bot-roger-gallet-rose-wellbeing-soap-100g-i.3701436910037",
  "name": "Xà Phòng Tạo Bọt Roger & Gallet Rose Wellbeing Soap 100g",
  "brandName": "ROGER &amp; GALLET",
  "barcode": "3701436910037",
  "statusText": "Hết hàng",
  "inStock": false,
  "remainingQuantityText": null,
  "branchesInStockText": null,
  "price": 209000,
  "originalPrice": 220000,
  "flashSalePrice": 209000,
  "discountPct": 5,
  "description": "Xà Phòng Tạo Bọt Roger & Gallet Rose Wellbeing Soap 100g với công thức chứa 97% thành phần có nguồn gốc tự nhiên mang lại cảm giác chăm sóc nhẹ nhàng, phù hợp với mọi loại da, kể cả da nhạy cảm. Tinh dầu hoa hồng tự nhiên trong xà phòng không chỉ làm sạch mà còn mang lại cảm giác thư giãn. Lớp bọt mỏng nhẹ bao bọc làn da với hương thơm ngọt ngào, tinh tế và lưu lại trên da suốt ngày dài. Hương thơm đặc trưng được tạo nên từ sự kết hợp của hoa hồng Nepal, quýt, hoa mẫu đơn, và nốt hổ phách mềm mại. Sản phẩm được sản xuất theo phương pháp truyền thống từ năm 1879, đảm bảo chất lượng vượt trội với bọt xà phòng mịn màng, giữ được hương thơm cho đến lần sử dụng cuối cùng. Xà Phòng Roger & Gallet Rose Wellbeing Soap không chỉ làm sạch mà còn dưỡng da mềm mại nhờ các thành phần như glycerin và chiết xuất hoa hồng Rosa Gallica. Đồng thời, công thức 100% thực vật và dễ phân hủy sinh học, thân thiện với môi trường. Hiện tại, Xà Phòng Tạo Bọt Roger & Gallet Rose Wellbeing Soap 100g đã có tại hệ thống các cửa hàng của Cocolux, bạn còn chần chờ gì nữa mà không thêm \"em nó\" vào giỏ hàng ngay thôi nào!",
  "benefits": null,
  "usage": null,
  "ingredients": null,
  "breadcrumb": [
    "Trang chủ",
    "Xà Phòng"
  ],
  "galleryImages": [
    "https://cocolux.com/storage/upload_image/images/xa-phong-roger-gallet-rose-wellbeing-soap-100g(2).jpg"
  ],
  "crawledAt": "2026-04-14T20:45:29.666Z"
}