{
  "url": "https://cocolux.com/kem-nen-catrice-18h-020-i.4059729331786",
  "name": "Kem Nền Catrice All Matt Shine Control Make-up 18h 30ml - Màu sắc:020",
  "brandName": "CATRICE",
  "barcode": "4059729331786",
  "statusText": "Hết hàng",
  "inStock": false,
  "remainingQuantityText": "Còn 4 sản phẩm",
  "branchesInStockText": null,
  "price": 137000,
  "originalPrice": 210000,
  "flashSalePrice": 137000,
  "discountPct": 34.76,
  "description": "Ra đời trên dây chuyền sản xuất hiện đại cùng bảng thành phần an toàn được kiểm nghiệm gắt gao, Kem nền Catrice 18H sở hữu nhiều công dụng cực kỳ đáng nể như: tạo lớp nền hoàn hảo, độ che phủ cao, đồng thời cấp ẩm và giữ ẩm hiệu quả giúp lớp makeup không bị trôi. bảo vệ làn da tối ưu trước sự tấn công của môi trường bên ngoài suốt 18h đồng hồ. Bên cạnh đó, với khả năng kiểm soát dầu nhờn vượt trội, kem nền Catrice 18H được xem là “cứu tinh” của làn da dầu, da nhạy cảm và có nhiều khuyết điểm. Đặc biệt, sản phẩm còn được chứng minh có khả năng làm sáng da, làm mờ các vết đốm nâu và giảm kích ứng. Sản phẩm đã có mặt tại Cocolux với 3 tone màu bán chạy nhất hiện nay, đó là: Kem nền Catrice 18H - 010: Tone sáng Kem nền Catrice 18H - 015: Tone Sáng – Trung bình Kem nền Catrice 18H - 020: Tone Tự nhiên",
  "benefits": null,
  "usage": null,
  "ingredients": null,
  "breadcrumb": [
    "Trang chủ",
    "Kem Nền - BB Cream"
  ],
  "galleryImages": [
    "https://cocolux.com/storage/upload_image/images/cdn_images/2022/06/images/products/1656310849062-t%E1%BA%A3i-xu%E1%BB%91ng.jpeg"
  ],
  "crawledAt": "2026-04-14T20:13:31.976Z"
}