{
  "url": "https://cocolux.com/tay-da-chet-body-organic-huong-dau-rung-250ml-i.4744183012639",
  "name": "Tẩy Tế Bào Chết Body Organic Shop Hương Dâu Rừng 250ml",
  "brandName": "ORGANIC SHOP",
  "barcode": "4744183012639",
  "statusText": "Hết hàng",
  "inStock": false,
  "remainingQuantityText": null,
  "branchesInStockText": null,
  "price": 135000,
  "originalPrice": 135000,
  "flashSalePrice": 135000,
  "discountPct": 0,
  "description": "Tẩy Da Chết Body Organic Shop là dòng sản phẩm tẩy da chết có nguồn gốc từ thiên nhiên, với các thành phần hữu cơ, tự nhiên giàu công dụng làm sạch và dưỡng da. Organic Shop gồm 13 sản phẩm với các thành phần chính khác nhau, mỗi loại lại có công dụng dưỡng da nhất định, kết hợp cùng đường, đem lại hiệu quả làm sạch sâu và dưỡng da hiệu quả. Hiện tại, Tẩy Da Chết Body Organic Shop đang có sẵn tại Cocolux với những phân loại như sau: Tẩy Da Chết Body Organic Shop Brazilian Coffee Body Scrub Tẩy Da Chết Body Organic Shop Brazilian Coffee Body Scrub có thành phần chính là hạt cà phê giúp loại bỏ bụi bẩn, dầu thừa, bã nhờn, tế bào chết trên da, chống oxy hoá da. Không chỉ có vậy, hàm lượng caffeine cao trong cà phê sẽ giúp dưỡng sáng, làm đều màu da, tăng cường độ săn chắc, khoẻ khoắn của làn da. Sản phẩm mang hương cà phê nhẹ nhàng, cho bạn thư giãn, thoải mái khi sử dụng sản phẩm. Tẩy Tế Bào Chết Body Organic Đu Đủ 250ml Tẩy Tế Bào Chết Body Organic Đu Đủ 250ml với thành phần chính chiết xuất đu đủ giúp làm sạch da, đem lại làn da thông thoáng, dưỡng sáng và làm mềm da. Hương thơm trái cây ngọt ngào, dịu nhẹ sẽ giúp bạn thư giãn, thoải mái khi sử dụng sản phẩm. Tẩy Tế Bào Chết Body Organic Hương Dâu Rừng 250ml Tẩy Tế Bào Chết Body Organic Hương Dâu Rừng 250ml nổi bật với thành phần chính là mâm xôi (hay còn gọi là dâu rừng) giàu vitamin E và vitamin C, giúp dưỡng sáng da, chống lão hoá, bảo vệ da khỏi các tác nhân gây hại bên ngoài môi trường, đặc biệt là tia UV. Sản phẩm mang hương thơm cùa dâu rừng nhẹ nhàng, dễ chịu. Tẩy Tế Bào Chết Body Organic Mật Ong Quế 250ml Tẩy Tế Bào Chết Body Organic Mật Ong Quế 250ml là sự kết hợp của hai thành phần thiên nhiên là quế và mật ong. Trong đó, quế giúp loại bỏ tế bào chết, bụi bẩn, bã nhờn và dầu thừa còn sót lại trên da. Mật ong giúp cấp ẩm, cân bằng độ ẩm tự nhiên trên da và bổ sung các dưỡng chất, nuôi dưỡng làn da mịn màng, trẻ trung, tái tạo làn da bị tổn thương. Sản phẩm mang mùi thơm nhẹ nhàng, không quá cay nồng của quế và mật ong. Tẩy Da Chết Organic Rose & Salt 250ml Tẩy Da Chết Organic Rose & Salt 250ml nổi bật với thành phần chính chứa nước hoa hồng có khả năng làm sạch da, giảm nhờn, làm thông thoáng lỗ chân lông, chống oxy hoá, dưỡng ẩm trên da. Sản phẩm mang mùi hoa hồng dịu nhẹ, cho bạn cảm giác thư giãn, thoải mái khi sử dụng.",
  "benefits": null,
  "usage": null,
  "ingredients": null,
  "breadcrumb": [
    "Trang chủ",
    "Tẩy Da Chết Body"
  ],
  "galleryImages": [
    "https://cocolux.com/storage/upload_image/images/cdn_images/2021/11/images/products/1636600767396-tay-te-bao-chet-body-organic-huong-dau-rung-250ml.jpeg"
  ],
  "crawledAt": "2026-04-14T20:39:38.417Z"
}