{
  "url": "https://cocolux.com/lotion-curel-duong-da-cap-am-chuyen-sau-ii-150ml-i.4901301236197",
  "name": "Lotion Curel Dưỡng Da Cấp Ẩm Chuyên Sâu II 150ml",
  "brandName": "Curél",
  "barcode": "4901301236197",
  "statusText": "Còn hàng",
  "inStock": true,
  "remainingQuantityText": "Còn 61 sản phẩm",
  "branchesInStockText": null,
  "price": 407300,
  "originalPrice": 498800,
  "flashSalePrice": 407300,
  "discountPct": 18.34,
  "description": "Lotion dưỡng da cấp ẩm Curél Face Lotion 150ml dành cho làn da khô và nhạy cảm, sản phẩm cung cấp độ ẩm, giúp da trở nên mịn màng và khỏe mạnh. Thành phần chính của lotion bao gồm Ceramide chức năng và chiết xuất lá khuynh diệp (Eucalyptus), mang lại hiệu quả dưỡng ẩm sâu và tạo lớp màng bảo vệ tự nhiên cho da. Lotion Curél thẩm thấu sâu vào các lớp biểu bì, tăng cường khả năng giữ ẩm và bảo vệ da khỏi các tác động bên ngoài. Curél Face Lotion đặc biệt nổi bật với khả năng kích thích da tự sản sinh Ceramide tự nhiên, cải thiện làn da khô ráp và làm dịu các vùng da bị kích ứng. Đây là bước dưỡng da lý tưởng, giúp các sản phẩm dưỡng da tiếp theo được hấp thụ tốt hơn, mang lại hiệu quả tối ưu trong quá trình chăm sóc da hàng ngày. Lotion Curél Face Lotion đã được kiểm nghiệm da liễu, đảm bảo không gây kích ứng cho da. Sản phẩm không chứa màu, không mùi và không cồn, hoàn toàn an toàn cho làn da nhạy cảm. Curél Face Lotion là lựa chọn hoàn hảo cho làn da khô và nhạy cảm, mang lại sự tươi trẻ và rạng rỡ cho làn da của bạn. Hiện Lotion Curel dưỡng da cấp ẩm chuyên sâu 150ml đang được phân phối tại Cocolux với 2 phân loại: Curél Face Lotion I: Dưỡng ẩm mức độ nhẹ Curél Face Lotion II: Dưỡng ẩm mức độ vừa",
  "benefits": null,
  "usage": null,
  "ingredients": null,
  "breadcrumb": [
    "Trang chủ",
    "Lotion/Sữa Dưỡng"
  ],
  "galleryImages": [
    "https://cocolux.com/storage/upload_image/images/cdn_images/2021/02/products/1613812478052-lotion-curel-duong-da-cap-am-chuyen-sau-ii.jpeg"
  ],
  "crawledAt": "2026-04-14T20:19:17.430Z"
}