{
  "url": "https://cocolux.com/tay-da-chet-moi-hu-beauty-treats-lip-scurb-i.676768105013",
  "name": "Tẩy Da Chết Môi Beauty Treats Lip Scrub",
  "brandName": "BEAUTY TREATS",
  "barcode": "676768105013",
  "statusText": "Hết hàng",
  "inStock": false,
  "remainingQuantityText": null,
  "branchesInStockText": null,
  "price": 75000,
  "originalPrice": 75000,
  "flashSalePrice": 75000,
  "discountPct": 0,
  "description": "Với thành phần có chứa các hạt scrub siêu nhỏ cùng các vitamin giàu dưỡng chất, Tẩy Da Chết môi hũ Beauty Treats Lip Scrub không chỉ giúp loại bỏ sạch sâu lớp da chết sần sùi mà còn bổ sung dưỡng chất cần thiết đem lại đôi môi căng mịn, mềm mại tự nhiên. Sản phẩm đang được bày bán tại hệ thống cửa hàng của Cocolux với 4 phân loại sau: Almond Creme: Hương Hạnh Nhân Wild Apple: Hương Táo Vanilla Bean: Hương Vani Dark Cherry: Hương Cherry",
  "benefits": null,
  "usage": null,
  "ingredients": null,
  "breadcrumb": [
    "Trang chủ",
    "Tẩy Tế Bào Chết Môi"
  ],
  "galleryImages": [
    "https://cocolux.com/storage/upload_image/images/cdn_images/2020/12/products/1608353114539-tay-da-chet-moi-hu-beauty-treats-lip-scurb.jpeg"
  ],
  "crawledAt": "2026-04-14T20:41:57.231Z"
}