{
  "url": "https://cocolux.com/kem-che-khuyet-diem-maybelline-min-li-05-Ivory-6-8ml-i.6902395685869",
  "name": "Kem Che Khuyết Điểm Maybelline Mịn Lì 05 Ivory 6.8ml",
  "brandName": "MAYBELLINE",
  "barcode": "6902395685869",
  "statusText": "Còn hàng",
  "inStock": true,
  "remainingQuantityText": "Còn 70 sản phẩm",
  "branchesInStockText": null,
  "price": 179000,
  "originalPrice": 188000,
  "flashSalePrice": 179000,
  "discountPct": 4.79,
  "description": "Kem che khuyết điểm Maybelline mịn lì 05 Ivory 6.8ml giúp bạn che phủ các khuyết điểm trên da một cách tự nhiên và hoàn hảo. Với chất kem dạng lỏng mịn, sản phẩm có độ che phủ cao và giúp làm mờ các vết mụn, vết nám, tàn nhang, thâm và mẩn đỏ trên da. Kem che khuyết điểm giúp bạn tạo ra một lớp nền tự nhiên và không gây cảm giác dày cộm trên da. Kem che khuyết điểm Maybelline phù hợp cho mọi loại da, cả da dầu và da có mụn. Sản phẩm không gây tắc nghẽn lỗ chân lông và kiểm soát dầu thừa trên da, giúp da bạn luôn mềm mịn và không bị bóng nhờn. Sản phẩm có độ bền cao, giúp duy trì lớp trang điểm hoàn hảo trong thời gian dài. Với kem che khuyết điểm Maybelline, bạn có thể tự tin che phủ các khuyết điểm trên da một cách tự nhiên và hiệu quả. Sản phẩm này là một phần không thể thiếu trong bộ sưu tập trang điểm của bạn, mang lại cho bạn một vẻ ngoài hoàn hảo và tự tin mỗi ngày.",
  "benefits": null,
  "usage": null,
  "ingredients": null,
  "breadcrumb": [
    "Trang chủ",
    "Che Khuyết Điểm"
  ],
  "galleryImages": [
    "https://cocolux.com/storage/upload_image/images/cdn_images/2023/06/images/products/1687323249940-kem-che-khuyet-diem-maybelline-min-li-05-(1).jpeg"
  ],
  "crawledAt": "2026-04-14T19:48:31.779Z"
}