{
  "url": "https://cocolux.com/co-che-khuyet-diem-xeo-dau-vacosi-round-concealer-brush-f15-i.6970758099431",
  "name": "Cọ Che Khuyết Điểm Xéo Đầu Vacosi Round Concealer Brush - F15",
  "brandName": "VACOSI",
  "barcode": "6970758099431",
  "statusText": "Còn hàng",
  "inStock": true,
  "remainingQuantityText": "Còn 38 sản phẩm",
  "branchesInStockText": null,
  "price": 47000,
  "originalPrice": 49000,
  "flashSalePrice": 47000,
  "discountPct": 4.08,
  "description": "Cọ Che Khuyết Điểm Xéo Đầu Vacosi Round Concealer Brush - F15 là sản phẩm cọ trang điểm đến từ thương hiệu Vacosi, được thiết kế chuyên biệt để dễ dàng che các khuyết điểm trên khuôn mặt. Đầu cọ được thiết kế độc đáo với đầu vát xéo cùng lông cọ mềm mại giúp bạn hô biến các vết mụn, thâm nám, tàn nhang... nhanh chóng. Đặc biệt, Cọ Che Khuyết Điểm Xéo Đầu Vacosi Round Concealer Brush - F15 còn có thể thay thế tạo khối mũi, cằm và hai bên gò má giúp đường nét trên khuôn mặt trở nên hài hòa hơn. Sản phẩm đã có tại các cơ sở của Cocolux, bạn còn chần chừ gì nữa mà không đến ngay cơ sở gần nhất để rinh em nó về cho tủ đồ makeup của mình!",
  "benefits": null,
  "usage": null,
  "ingredients": null,
  "breadcrumb": [
    "Trang chủ",
    "Cọ Trang Điểm"
  ],
  "galleryImages": [
    "https://cocolux.com/storage/upload_image/images/san-pham/co-che-khuyet-diem-xeo-dau-vacosi-round-concealer-brush-f15.jpg"
  ],
  "crawledAt": "2026-04-14T19:50:12.525Z"
}