{
  "url": "https://cocolux.com/mieng-dan-mun-lanbena-invisible-acne-pimple-ban-dem-i.6975497992999",
  "name": "Miếng Dán Mụn Lanbena Invisible Acne Pimple Ban Đêm",
  "brandName": "LANBENA",
  "barcode": "6975497992999",
  "statusText": "Còn hàng",
  "inStock": true,
  "remainingQuantityText": "Còn 125 sản phẩm",
  "branchesInStockText": null,
  "price": 67000,
  "originalPrice": 79000,
  "flashSalePrice": 67000,
  "discountPct": 15.19,
  "description": "Miếng Dán Mụn Lanbena Invisible Acne Pimple Patch là sản phẩm hỗ trợ xử lý mụn nhanh chóng với thiết kế mỏng nhẹ, trong suốt, giúp bảo vệ nốt mụn khỏi vi khuẩn và bụi bẩn. Sản phẩm sử dụng chất liệu hydrocolloid giúp hấp thụ dịch mụn, giảm viêm và hỗ trợ làm xẹp mụn nhanh hơn, đồng thời tạo lớp màng bảo vệ giúp hạn chế sẹo và thâm. Cocolux hiện đang phân phối 2 phiên bản: Ban ngày (Day Use): Mỏng, gần như “invisible”, có thể dùng dưới makeup Ban đêm (Night Use): Dày hơn, hút dịch mụn mạnh hơn, phù hợp khi ngủ",
  "benefits": null,
  "usage": null,
  "ingredients": null,
  "breadcrumb": [
    "Trang chủ",
    "Trị Mụn"
  ],
  "galleryImages": [
    "https://cocolux.com/upload/product/6975497992999.webp"
  ],
  "crawledAt": "2026-04-14T20:01:07.848Z"
}