{
  "url": "https://cocolux.com/kem-tri-nam-dongsung-70g-i.8807050015877",
  "name": "Kem Dưỡng DongSung Hỗ Trợ Giảm Nám, Dưỡng Sáng Da 70g",
  "brandName": "DongSung",
  "barcode": "8807050015877",
  "statusText": "Hết hàng",
  "inStock": false,
  "remainingQuantityText": null,
  "branchesInStockText": null,
  "price": 450000,
  "originalPrice": 450000,
  "flashSalePrice": 450000,
  "discountPct": 0,
  "description": "Kem Dưỡng DongSung Hỗ Trợ Giảm Nám, Dưỡng Sáng Da 70g là một trong số những thành phần nổi bật của thương hiệu DongSung. Sản phẩm chứa nhiều dưỡng chất như nọc ong, nhau thai kết hợp với hoạt chất Alpha-Bisabolol, Kojic Acid giúp làm giảm vết thâm, nám, tàn nhang, thâm nám, đồi mồi, giảm độc tố trên da và dưỡng trắng, cải thiện làn da sáng hồng từ sâu bên trong. Chỉ sau 1 thời gian ngắn sử dụng, bạn sẽ cảm nhận được sự thay đổi rõ rệt trên làn da của mình.",
  "benefits": null,
  "usage": null,
  "ingredients": null,
  "breadcrumb": [
    "Trang chủ",
    "Trị Nám - Tàn Nhang"
  ],
  "galleryImages": [
    "https://cocolux.com/storage/upload_image/images/cdn_images/2021/01/products/1611299889782-kem-tri-nam-dong-sung-70g-1.jpeg"
  ],
  "crawledAt": "2026-04-14T20:01:43.942Z"
}