{
  "url": "https://cocolux.com/kem-lot-klavuu-white-pearlsation-ideal-actress-backstage-cream-spf30-pa++-rose-i.8809482366947",
  "name": "Kem Lót Klavuu White Pearlsation Ideal Actress Backstage Cream SPF30 PA++ Rose",
  "brandName": "KLAVUU",
  "barcode": "8809482366947",
  "statusText": "Còn hàng",
  "inStock": true,
  "remainingQuantityText": "Còn 69 sản phẩm",
  "branchesInStockText": null,
  "price": 299000,
  "originalPrice": 359000,
  "flashSalePrice": 299000,
  "discountPct": 15,
  "description": null,
  "benefits": null,
  "usage": null,
  "ingredients": null,
  "breadcrumb": [
    "Trang chủ",
    "Kem Lót"
  ],
  "galleryImages": [
    "https://cocolux.com/upload/product/8809482366947.webp"
  ],
  "crawledAt": "2026-04-14T20:11:11.375Z"
}