{
  "url": "https://cocolux.com/mieng-dan-tri-mun-some-by-mi-clear-spot-patch-i.8809647390015",
  "name": "Miếng Dán Mụn Some By Mi Clear Spot Patch 18 PCS",
  "brandName": "SOME BY MI",
  "barcode": "8809647390015",
  "statusText": "Hết hàng",
  "inStock": false,
  "remainingQuantityText": null,
  "branchesInStockText": null,
  "price": 86000,
  "originalPrice": 107000,
  "flashSalePrice": 86000,
  "discountPct": 19.63,
  "description": "Some By Mi được biết đến là thương hiệu mỹ phẩm được nhiều người lựa chọn tại Hàn Quốc. Với những dòng sản phẩm chất lượng có giá hợp lý, mỹ phẩm Some By Mi luôn phát huy thế mạnh về các sản phẩm hỗ trợ trị mụn, tiêu biểu như Miếng Dán Mụn Some By Mi Clear Spot Patch. Đây là sản phẩm có công dụng kháng viêm giảm sưng và giúp làm lành vết thương do mụn mà không cần phải can thiệp bởi các phương pháp cơ học như nặn mụn. Miếng Dán Mụn Some By Mi Clear Spot Patch 18pcs được coi như “cứu tinh” khi da gặp phải vấn đề về mụn. Sản phẩm có chứa hoạt chất kháng viêm ngăn ngừa quá trình sưng tấy, làm dịu da và hạn chế tình trạng thâm sau mụn. Sản phẩm sử dụng công thức độc quyền của SOME BY MI, sở hữu khả năng hấp thu nhân mụn, kháng viêm hiệu quả sẽ là lựa chọn hoàn hảo dành cho những làn da đang gặp vấn đề về mụn. Sản phẩm có thiết kế siêu mỏng và dễ sử dụng, tiệp với màu da không gây mất thẩm mỹ, nhanh chóng làm giảm mụn chỉ sau 8 giờ dán. Hiện tại, Cocolux đang phân phối song song cả mẫu mới và mẫu cũ của sản phẩm Miếng Dán Mụn Some By Mi Clear Spot Patch 18pcs vì vậy bạn có thể nhận 1 trong 2 phiên bản dưới đây, tuy nhiên chất lượng của sản phẩm không thay đổi.",
  "benefits": null,
  "usage": null,
  "ingredients": null,
  "breadcrumb": [
    "Trang chủ",
    "Trị Mụn"
  ],
  "galleryImages": [
    "https://cocolux.com/upload/product/tri-mun/mieng-dan-tri-mun-some-by-mi-clear-spot-patch-1.webp"
  ],
  "crawledAt": "2026-04-14T20:01:32.842Z"
}